model_explorer_onnx/__init__.py
model_explorer_onnx/_passes.py
model_explorer_onnx/main.py
model_explorer_onnx/torch_utils.py
model_explorer_onnx/bin/__init__.py
model_explorer_onnx/bin/onnxvis.py
model_explorer_onnx-0.4.0.dist-info/licenses/LICENSE
model_explorer_onnx-0.4.0.dist-info/METADATA
model_explorer_onnx-0.4.0.dist-info/WHEEL
model_explorer_onnx-0.4.0.dist-info/entry_points.txt
model_explorer_onnx-0.4.0.dist-info/top_level.txt
model_explorer_onnx-0.4.0.dist-info/RECORD
