Metadata-Version: 2.4
Name: model-explorer-onnx
Version: 0.4.0
Summary: Adapter for ai-edge-model-explorer to support ONNX models
Author-email: Justin Chu <justinchu@microsoft.com>
License-Expression: MIT
Project-URL: Repository, https://github.com/justinchuby/model-explorer-onnx
Keywords: onnx,model-explorer,visualization
Classifier: Development Status :: 4 - Beta
Classifier: Intended Audience :: Developers
Classifier: Operating System :: POSIX
Classifier: Operating System :: MacOS :: MacOS X
Classifier: Operating System :: Microsoft :: Windows
Requires-Python: >=3.9
License-File: LICENSE
Requires-Dist: ai-edge-model-explorer>=0.1.10
Requires-Dist: numpy
Requires-Dist: onnx
Requires-Dist: onnx_ir>=0.1.13
Dynamic: license-file
